{
    "apparel_category": "All Bras, Lingerie, Swimsuits & Shapewear",
    "product_type": [
        "Bras",
        "Lingerie",
        "Swimsuits",
        "Shapewear"
    ],
    "guideline_concept": "Additional Attributes",
    "guidelines": {
        "guideline_type": "Naming Guidelines",
        "attribute_requirements": [
            {
                "step_name": "Bra Size",
                "description": "Bra size, consisting of band and cup. Use this attribute if the garment has both measurements."
            },
            {
                "step_name": "Bra Band Size",
                "description": "Measurement in inches of the band of the bra, fitting around the ribcage."
            },
            {
                "step_name": "Bra Cup Size",
                "description": "Letter size to optimize bra fit, using chest measurements."
            },
            {
                "step_name": "Bra Feature",
                "description": "Features specific to brassieres that garments can have."
            }
        ]
    },
    "graph": [
        {
            "linkage": "All Bras, Lingerie, Swimsuits & Shapewear-(Apparel_Category)->Bras-(Product_Type)->Naming Guidelines-(attribute_requirements)"
        },
        {
            "linkage": "All Bras, Lingerie, Swimsuits & Shapewear-(Apparel_Category)->Lingerie-(Product_Type)->Naming Guidelines-(attribute_requirements)"
        },
        {
            "linkage": "All Bras, Lingerie, Swimsuits & Shapewear-(Apparel_Category)->Swimsuits-(Product_Type)->Naming Guidelines-(attribute_requirements)"
        },
        {
            "linkage": "All Bras, Lingerie, Swimsuits & Shapewear-(Apparel_Category)->Shapewear-(Product_Type)->Naming Guidelines-(attribute_requirements)"
        }
    ],
    "summary": "The page outlines mandatory attributes for bras, lingerie, swimsuits, and shapewear with bras or built-in bras, emphasizing the importance of various size measurements and features to ensure items meet Walmart's style guide standards."
}