{
    "apparel_category": null,
    "product_type": null,
    "guideline_concept": "Copy Standards",
    "guidelines": {
        "guideline_type": "Copy Standards",
        "writing_guidelines": [
            {
                "step_name": "Attract Customers",
                "description": "Great copy can attract more customers through SEO and SEM."
            },
            {
                "step_name": "Conversion Optimization",
                "description": "Effective writing helps customers convert and reduces returns."
            },
            {
                "step_name": "Legal Requirements",
                "description": "Include legally obligated copy and formatting requirements."
            }
        ]
    },
    "graph": [
        {
            "linkage": "Guideline_Concept -> Guideline_Type -> writing_guidelines"
        }
    ]
}