{
    "apparel_category": "Socks & Hosiery",
    "product_type": "Hosiery Garments",
    "guideline_concept": "Key Feature Directions",
    "guidelines": {
        "guideline_type": "Key Feature Directions",
        "key_feature_details": [
            {
                "step_name": "Material",
                "description": "Fabric content including linings & any trims 5% or more of makeup."
            },
            {
                "step_name": "Care",
                "description": "Spot clean, Machine wash cold, etc."
            },
            {
                "step_name": "Size Ranges",
                "description": "Include height and weight, if available."
            },
            {
                "step_name": "Fits",
                "description": "Sizes X-XX."
            }
        ]
    },
    "graph": [
        {
            "linkage": "Apparel_Category -> Product_Type -> Guideline_Type -> key_feature_details"
        },
        {
            "linkage": "Guideline_Concept -> Guideline_Type -> key_feature_details"
        }
    ]
}